{"backend_container_vim.md":"0300bb3c","backend_java_idea.md":"7068d584","backend_java_oop.md":"e08301ef","database_mysql.md":"08713125","backend_container_podman.md":"ce181af2","backend_java_springboot.md":"2dafc32e","backend_java_biyi.md":"a4efae9c","frontend_react_reactjs.md":"a0dd5106","frontend_solid_solidjs.md":"fd317fed","frontend_web_big-screen.md":"f6ee190b","frontend_web_creativity.md":"747c2965","frontend_web_css.md":"2011b97c","network_caddy2.md":"46910b63","guide_about-me.md":"ffb33d95","frontend_feast_typescript.md":"abebe819","guide_connect-me.md":"f3cab26d","index.md":"39831ccd","frontend_web_site.md":"aae818c9","jicao_daynight.md":"2f2fe10f","frontend_service_error.md":"cd3f150d","network_nginx.md":"a836de68","frontend_react_jsx.md":"31214d1a","frontend_service_useful.md":"8388d214","backend_container_linux.md":"c9f25b49","frontend_feast_plugins.md":"bde938a1","frontend_feast_package-manage.md":"d8984069","frontend_vue_vuejs.md":"2860f7a2"}
